swagger_client/__init__.py
swagger_client/api_client.py
swagger_client/configuration.py
swagger_client/rest.py
swagger_client/api/__init__.py
swagger_client/api/attachment_api.py
swagger_client/api/auth_systems_api.py
swagger_client/api/automation_job_api.py
swagger_client/api/build_api.py
swagger_client/api/common_api.py
swagger_client/api/defect_api.py
swagger_client/api/field_api.py
swagger_client/api/groups_api.py
swagger_client/api/integration_settings_api.py
swagger_client/api/login_api.py
swagger_client/api/module_api.py
swagger_client/api/object_link_api.py
swagger_client/api/project_api.py
swagger_client/api/release_api.py
swagger_client/api/requirement_api.py
swagger_client/api/search_api.py
swagger_client/api/site_templates_api.py
swagger_client/api/test_case_api.py
swagger_client/api/test_cycle_api.py
swagger_client/api/test_log_api.py
swagger_client/api/test_run_api.py
swagger_client/api/test_suite_api.py
swagger_client/api/tosca_api.py
swagger_client/api/user_api.py
swagger_client/api/user_profile_api.py
swagger_client/api/webhook_api.py
swagger_client/models/__init__.py
swagger_client/models/admin_profile.py
swagger_client/models/allowed_value_input_resource.py
swagger_client/models/allowed_value_resource.py
swagger_client/models/allowed_value_response_resource.py
swagger_client/models/app_detail.py
swagger_client/models/apply_template_query_object.py
swagger_client/models/artifact_history_resource.py
swagger_client/models/artifact_search_params.py
swagger_client/models/assigned_project.py
swagger_client/models/assigned_users_project.py
swagger_client/models/attachment_author.py
swagger_client/models/attachment_resource.py
swagger_client/models/auth_system_response.py
swagger_client/models/authority_vm.py
swagger_client/models/auto_fill_configuration_vm.py
swagger_client/models/automation_artifact_search_params.py
swagger_client/models/automation_fail_linked_defect_response.py
swagger_client/models/automation_linked_defect_response.py
qtest_swagger_client-0.0.3.dist-info/METADATA
qtest_swagger_client-0.0.3.dist-info/WHEEL
qtest_swagger_client-0.0.3.dist-info/top_level.txt
qtest_swagger_client-0.0.3.dist-info/RECORD
